tonina/__init__.py
tonina/main.py
tonina/agents/__init__.py
tonina/agents/general_agent/__init__.py
tonina/agents/general_agent/general_agent.py
tonina/agents/general_agent/general_tools.py
tonina/agents/gff_agent/__init__.py
tonina/agents/gff_agent/gff_agent.py
tonina/agents/gff_agent/gff_tools.py
tonina/core/__init__.py
tonina/core/agent_manager.py
tonina/core/base_agent.py
tonina/core/router.py
tonina/prompts/general_prompt.txt
tonina/prompts/gff_prompt.txt
tonina/tools/__init__.py
tonina/tools/file_operations.py
tonina-0.1.0.dist-info/METADATA
tonina-0.1.0.dist-info/WHEEL
tonina-0.1.0.dist-info/entry_points.txt
tonina-0.1.0.dist-info/top_level.txt
tonina-0.1.0.dist-info/RECORD
