Metadata-Version: 2.4
Name: tonina
Version: 0.1.0
Summary: Multi-agent bioinformatics analysis system with comprehensive capabilities
License-Expression: GPL-3.0
Project-URL: Homepage, https://github.com/ToyokoLabs/tonina
Project-URL: Repository, https://github.com/ToyokoLabs/tonina
Requires-Python: >=3.12
Requires-Dist: gffutils>=0.13
Requires-Dist: strands-agents[anthropic,gemini,ollama,openai]>=1.10.0
Requires-Dist: strands-agents-tools>=0.2.9
Requires-Dist: biopython>=1.85
Requires-Dist: python-dotenv>=1.0.0
